{
  "templateType": "Apprenticeship Standard",
  "larsCode": 306,
  "referenceNumber": "ST0582",
  "learningAimClassCode": "",
  "title": "Operating department practitioner (integrated degree)",
  "status": "Retired",
  "approvedForDeliveryPausedStarts": null,
  "url": "https://instituteforapprenticeships.org/api/apprenticeshipstandards/ST0582",
  "qualificationStandardUrl": null,
  "versionNumber": "1.0",
  "change": "Approved for delivery",
  "changedDate": "2022-11-30T00:00:00",
  "earliestStartDate": "2018-06-28T00:00:00",
  "latestStartDate": "2022-10-31T00:00:00",
  "latestEndDate": null,
  "overviewOfRole": "Supporting operating theatre staff and providing care to patients at all stages of an operation.",
  "level": 6,
  "ePALength": 0,
  "typicalDuration": 48,
  "maxFunding": 24000,
  "maxFundingAdditionalInformation": "",
  "route": "Health and science",
  "keywords": [
    "operating department practitioner",
    "degree",
    "healthcare services",
    "Science",
    "practitioner",
    "health",
    "care"
  ],
  "jobRoles": [],
  "entryRequirements": "",
  "assessmentPlanUrl": "https://instituteforapprenticeships.org/media/1932/st05820-operating-department-practitoner-asssement-plan-for-publication.pdf",
  "ssa1": "1 Health, Public Services and Care",
  "ssa2": "1.2 Nursing, and subjects and vocations allied to medicine",
  "version": "1.0",
  "standardInformation": "&lt;h3&gt;&lt;strong&gt;Occupational profile:&lt;/strong&gt;&lt;/h3&gt;\n&lt;p&gt;Operating Department Practitioners (ODPs) are registered healthcare professionals specialising in caring for people of all ages before, during &amp;amp; after surgery. ODPs therefore mainly work in operating departments. They work alongside other professionals (such as doctors and nurses) and take a lead role in ensuring a patient is safe during each stage of a patient’s journey through the operating theatre. ODPs must continually make professional decisions to ensure the patient receives the best care before, during and after their surgery. ODPs also ensure that the operating theatre environment is safe and effective and therefore have expertise in the management of specialist equipment &amp;amp; materials in a highly technical environment, for example handling surgical instruments, checking anaesthetic equipment, moving patients and giving medication ODPs must demonstrate confidence, compassion, competence &amp;amp; effective judgement; being responsible for their decisions. They must use evidence based practice to inform &amp;amp; evaluate the effectiveness of the actions they take with the aim of continually improving outcomes for patients. They are responsible for ensuing their own professional knowledge and skills through continuous professional development (CPD)&amp;amp; support the development of others. &#160;&lt;/p&gt;\n&lt;h3&gt;&lt;strong&gt;Day to Day activities: &lt;/strong&gt;&lt;/h3&gt;\n&lt;h4&gt;&lt;strong&gt;Anaesthesia phase of care requires ODPs to:&lt;/strong&gt;&lt;/h4&gt;\n&lt;ul&gt;\n&lt;li&gt;Provide individualised care for patients prior to &amp;amp; throughout surgery or other procedures including reassurance &amp;amp; support during vulnerable times&lt;/li&gt;\n&lt;li&gt;Utilise a wide range of clinical skills knowledge &amp;amp; understanding to ensure a safe environment during the administration &amp;amp; maintenance of anaesthesia&lt;/li&gt;\n&lt;li&gt;Position patient to optimise surgical access. Maintain patient safety &amp;amp; dignity. Medicines management.&lt;/li&gt;\n&lt;li&gt;Prepare a wide range of specialist equipment &amp;amp; devices. Assist the anaesthetist in safely securing &amp;amp; maintaining the patients airway &amp;amp; physiological stability during anaesthesia&lt;strong&gt;. &lt;/strong&gt;&lt;/li&gt;\n&lt;/ul&gt;\n&lt;h4&gt;&lt;strong&gt;Surgery phase of care requires ODPs to:&lt;/strong&gt;&lt;/h4&gt;\n&lt;ul&gt;\n&lt;li&gt;Work as part of a team to provide safe individualised care to patients during surgery&lt;/li&gt;\n&lt;li&gt;Professionally responsible for selection, preparation &amp;amp; provision of the correct sterile surgical equipment to the surgeon &amp;amp; being accountable for all surgical instruments, equipment &amp;amp; swabs throughout the procedure&lt;/li&gt;\n&lt;li&gt;Anticipate the requirements of the surgical team, responding appropriately &amp;amp; effectively. Ensuring the correct management of clinical specimens&lt;/li&gt;\n&lt;/ul&gt;\n&lt;h4&gt;&lt;strong&gt;The Post Anaesthetic Care phase involves:&lt;/strong&gt;&lt;/h4&gt;\n&lt;p&gt;Caring for the patient whilst in the post anaesthetic care Unit (PACU). Observing &amp;amp; monitoring a patients vital signs. Maintaining their airway &amp;amp; identifying &amp;amp; responding to changes in the patients physiological &amp;amp; psychological condition. Providing appropriate treatment including pain control &amp;amp; post-operative nausea &amp;amp; vomiting care; until the patient has recovered from the immediate effects of anaesthesia &amp;amp; has been assessed in order to ensure they are fit to be discharged from PACU.&lt;/p&gt;\n&lt;h3&gt;&lt;strong&gt;Qualification requirements:&lt;/strong&gt;&lt;/h3&gt;\n&lt;p&gt;Apprentices will be required to complete a Health and Care Professions Council (HCPC) approved BSc (Hons) in Operating Department Practice&lt;strong&gt;&lt;em&gt;. &lt;/em&gt;&lt;/strong&gt;Apprentices without level 2 English &amp;amp; maths will need to achieve this level prior to completing the end-point assessment. For those with an education, health &amp;amp; care plan or a legacy statement, the apprenticeships English &amp;amp; maths minimum requirement is Entry Level 3 &amp;amp; British Sign Language qualification are an alternative to English qualifications for whom this is their primary language.&lt;/p&gt;\n&lt;h3&gt;&lt;strong&gt;Professional registration:&lt;/strong&gt;&lt;/h3&gt;\n&lt;p&gt;On successful completion of an approved programme, apprentices are eligible to apply to the HCPC for registration as an Operating Department Practitioner, which is a requirement to practice under the protected title of Operating Department Practitioner&lt;/p&gt;\n&lt;h3&gt;&lt;strong&gt;Additional information:&lt;/strong&gt;&lt;/h3&gt;\n&lt;p&gt;The apprentice must meet the 15 standards as set out in the &lt;a href=&quot;http://www.skillsforhealth.org.uk/standards/item/216-the-care-certificate&quot;&gt;Care Certificate&lt;/a&gt;&lt;a name=&quot;_ednref1&quot; href=&quot;#_edn1&quot;&gt;&lt;span&gt;[i]&lt;/span&gt;&lt;/a&gt; within 3 months of commencing an apprenticeship.&lt;/p&gt;\n&lt;h3&gt;Level: 6&#160;&lt;/h3&gt;\n&lt;h3&gt;Duration: Typically 4 years&#160;&lt;/h3&gt;\n&lt;h3&gt;Review date: After 3 years&#160;&lt;/h3&gt;\n&lt;table border=&quot;0&quot;&gt;\n&lt;tbody&gt;\n&lt;tr&gt;\n&lt;td&gt;&#160;&lt;/td&gt;\n&lt;th&gt;&lt;strong&gt;You will be able to:&lt;/strong&gt;&lt;/th&gt;\n&lt;th&gt;&lt;strong&gt;You will know and understand:&lt;/strong&gt;&lt;/th&gt;\n&lt;/tr&gt;\n&lt;tr&gt;\n&lt;td&gt;Professional practice&lt;/td&gt;\n&lt;td&gt;\n&lt;ul&gt;\n&lt;li&gt;Practice as an autonomous ODP, assessing patients in theatres &amp;amp; associated areas, exercising professional judgement to establish patient centred goals, &amp;amp; to accept, plan, initiate, modify, refer or cease treatment within prescribed limits&lt;/li&gt;\n&lt;li&gt;Recognise disease &amp;amp; trauma processes relevant to perioperative care&lt;/li&gt;\n&lt;li&gt;Accurately calculate &amp;amp; record prescribed drug doses&lt;/li&gt;\n&lt;li&gt;Change practice to account for new developments or changing contexts in what constitutes best practice in perioperative care,&#160; through effective change management&lt;/li&gt;\n&lt;li&gt;Respond appropriately&#160; to emergency situations&lt;/li&gt;\n&lt;li&gt;Conduct appropriate diagnostic, monitoring, treatment &amp;amp; therapy procedures safely &amp;amp; effectively&lt;/li&gt;\n&lt;li&gt;Undertake anaesthetic, surgical &amp;amp; post-anaesthesia care interventions including managing airways, cannulation, catheterisation &amp;amp; manual handling/positioning&lt;/li&gt;\n&lt;li&gt;Monitor airway, breathing &amp;amp; circulation&lt;/li&gt;\n&lt;li&gt;Monitor &amp;amp; record fluid balance &amp;amp; administer prescribed fluids appropriately&lt;/li&gt;\n&lt;li&gt;Monitor the effects of drugs &amp;amp; take appropriate action is response to significant change&lt;/li&gt;\n&lt;li&gt;Assess &amp;amp; monitor individuals pain status &amp;amp; administer prescribed pain relief appropriately&lt;/li&gt;\n&lt;li&gt;Select appropriate techniques &amp;amp; equipment; undertake &amp;amp; record thorough assessments &amp;amp; investigations.&lt;/li&gt;\n&lt;li&gt;Maintaining Basic, Intermediate or Advanced Life Support qualifications where appropriate&lt;/li&gt;\n&lt;li&gt;Assist anaesthesia with the use of medical devices &amp;amp; pharmacological (drugs) means&lt;/li&gt;\n&lt;li&gt;Maintain a sterile working area &amp;amp; safely &amp;amp; effectively perform aseptic technique (including scrubbing, gloving &amp;amp; gowning)&lt;/li&gt;\n&lt;li&gt;Perform scrub skills according in accordance with Perioperative Care Collaborative statement&lt;/li&gt;\n&lt;/ul&gt;\n&lt;/td&gt;\n&lt;td&gt;\n&lt;ul&gt;\n&lt;li&gt;How to apply professional knowledge, skills &amp;amp; experience in partnership with other professionals to optimise outcomes for patients&lt;/li&gt;\n&lt;li&gt;Normal anatomy &amp;amp; physiology of the human body &amp;amp; impact of disease, &amp;amp; trauma processes&lt;/li&gt;\n&lt;li&gt;Physiological parameters &amp;amp; how to interpret changes/deviations&lt;/li&gt;\n&lt;li&gt;How to order, store, issue, prepare &amp;amp; administer prescribed drugs &amp;amp; monitor their effects&lt;/li&gt;\n&lt;li&gt;The drugs that are used in ODP practice &amp;amp; how they affect the body&lt;/li&gt;\n&lt;li&gt;Safe practices in the use of medical devices use for diagnostic, monitoring or therapeutic purposes&lt;/li&gt;\n&lt;li&gt;Effective innovation, change management &amp;amp; planning techniques; theories of change mangement including tools &amp;amp; techniques in how to apply them&lt;/li&gt;\n&lt;li&gt;The principles &amp;amp; practices in the management of anaesthetic &amp;amp; surgical emergencies, e.g. a major haemorrhage or anaphylaxis.&lt;/li&gt;\n&lt;li&gt;The management &amp;amp; processes involved in the administration of blood &amp;amp; blood products&lt;/li&gt;\n&lt;li&gt;The use of research methodologies used in Operating Department Practice; the principles &amp;amp; applications of evidence based practice.&lt;/li&gt;\n&lt;li&gt;The principles of hand hygiene &amp;amp; asepsis&lt;/li&gt;\n&lt;li&gt;Sterilisation &amp;amp; decontamination of equipment processes&lt;/li&gt;\n&lt;li&gt;Safeguarding processes &amp;amp; how to raise concerns&lt;/li&gt;\n&lt;li&gt;Infection prevention &amp;amp; control policies &amp;amp; procedures&lt;/li&gt;\n&lt;li&gt;The role of the surgical first assistant in assisting with surgical interventions&lt;/li&gt;\n&lt;li&gt;Appropriate Moving &amp;amp; Handling Techniques&lt;/li&gt;\n&lt;li&gt;The structure &amp;amp; function of health &amp;amp; social care services in the UK&lt;/li&gt;\n&lt;/ul&gt;\n&lt;/td&gt;\n&lt;/tr&gt;\n&lt;tr&gt;\n&lt;td&gt;Professional values &amp;amp; behaviours&lt;/td&gt;\n&lt;td&gt;\n&lt;ul&gt;\n&lt;li&gt;Recognise &amp;amp; take account of needs &amp;amp; diversity of individuals&lt;/li&gt;\n&lt;li&gt;Shape or structure your practice according to evidence based practice&lt;/li&gt;\n&lt;li&gt;Practice in a manner ensuring equality &amp;amp; act as an advocate for patients. Demonstrate care, compassion, confidence, courage, communication &amp;amp; commitment for patients at their most vulnerable.&lt;/li&gt;\n&lt;li&gt;Maintain the patients dignity at all times&lt;/li&gt;\n&lt;li&gt;Demonstrate an open, honest &amp;amp; courteous approach to patients relatives &amp;amp; colleagues&lt;/li&gt;\n&lt;/ul&gt;\n&lt;/td&gt;\n&lt;td&gt;\n&lt;ul&gt;\n&lt;li&gt;How to assess the nature &amp;amp; complexity of a patients needs&lt;/li&gt;\n&lt;li&gt;How to adapt practice to meet the needs of patients within the scope of ODP practice, national/local policy &amp;amp; latest evidence&lt;/li&gt;\n&lt;li&gt;The importance of maintaining patients comfort &amp;amp; dignity at all times&lt;/li&gt;\n&lt;li&gt;The requirements of Duty of candour regulations&lt;/li&gt;\n&lt;li&gt;Legal &amp;amp; ethical issues pertinent to ODP practice&lt;/li&gt;\n&lt;li&gt;Theatre etiquette&lt;/li&gt;\n&lt;li&gt;How to interact with patients, relatives &amp;amp; colleagues in a professional manner&lt;/li&gt;\n&lt;/ul&gt;\n&lt;/td&gt;\n&lt;/tr&gt;\n&lt;tr&gt;\n&lt;td&gt;Professional standards&lt;/td&gt;\n&lt;td&gt;\n&lt;ul&gt;\n&lt;li&gt;Practice within the Health and Care Professions Council (HCPC) Standards of Proficiency for ODP’s&lt;a name=&quot;_ednref1&quot; href=&quot;#_edn1&quot;&gt;[i]&lt;/a&gt; &amp;amp; The College of Operating Department Practitioners Scope of Practice&lt;a name=&quot;_ednref2&quot; href=&quot;#_edn2&quot;&gt;[ii]&lt;/a&gt;&lt;/li&gt;\n&lt;/ul&gt;\n&lt;/td&gt;\n&lt;td&gt;\n&lt;ul&gt;\n&lt;li&gt;The legislation, standards and protocol relating to ODP practice&#160;&lt;a name=&quot;_ednref3&quot; href=&quot;#_edn3&quot;&gt;[iii]&lt;/a&gt;.&lt;/li&gt;\n&lt;/ul&gt;\n&lt;/td&gt;\n&lt;/tr&gt;\n&lt;/tbody&gt;\n&lt;/table&gt;\n&lt;table border=&quot;0&quot;&gt;\n&lt;tbody&gt;\n&lt;tr&gt;\n&lt;td&gt;&#160;&lt;/td&gt;\n&lt;th&gt;&lt;strong&gt;You will be able to:&lt;/strong&gt;&lt;/th&gt;\n&lt;th&gt;&lt;strong&gt;You will know and understand:&lt;/strong&gt;&lt;/th&gt;\n&lt;/tr&gt;\n&lt;tr&gt;\n&lt;td&gt;Leadership, management &amp;amp; partnership working&lt;/td&gt;\n&lt;td&gt;\n&lt;ul&gt;\n&lt;li&gt;Effectively lead manage &amp;amp; delegate colleagues, working as part of the surgical team&lt;/li&gt;\n&lt;li&gt;Work collaboratively throughout the patients perioperative journey with the surgical team &amp;amp; others&lt;/li&gt;\n&lt;li&gt;Use the evidence base to promote innovation &amp;amp; improvement in operating department practice&lt;/li&gt;\n&lt;li&gt;Actively participate in audit, training &amp;amp; review activities&lt;/li&gt;\n&lt;li&gt;Manage yourself in emergency &amp;amp; stressful situations.&lt;/li&gt;\n&lt;li&gt;Demonstrate self-awareness &amp;amp; impact on others.&lt;/li&gt;\n&lt;li&gt;Reflect on own practice &amp;amp; challenge self &amp;amp; others&lt;/li&gt;\n&lt;/ul&gt;\n&lt;/td&gt;\n&lt;td&gt;\n&lt;ul&gt;\n&lt;li&gt;The concept of leadership &amp;amp; using personal initiative&lt;/li&gt;\n&lt;li&gt;The value of participation in training, supervision &amp;amp; mentoring&lt;/li&gt;\n&lt;li&gt;The importance of working collaboratively with those who provide services&lt;/li&gt;\n&lt;li&gt;How to reflect effectively &amp;amp; facilitate change in perioperative practice&lt;/li&gt;\n&lt;li&gt;Team dynamics, communication &amp;amp; patient safety with a reference to human factors&lt;/li&gt;\n&lt;li&gt;The value &amp;amp; impact of research, audit &amp;amp; evaluation on operating department practice&lt;/li&gt;\n&lt;li&gt;The importance of maintaining own health &amp;amp; well-being; ways to manage &amp;amp; reduce occupational stress&lt;/li&gt;\n&lt;/ul&gt;\n&lt;/td&gt;\n&lt;/tr&gt;\n&lt;tr&gt;\n&lt;td&gt;\n&lt;p&gt;Communication &amp;amp; information&lt;/p&gt;\n&lt;/td&gt;\n&lt;td&gt;\n&lt;ul&gt;\n&lt;li&gt;Safeguard confidential information, relating to patients at all times, consistently applying data protection principles&lt;/li&gt;\n&lt;li&gt;Apply a range of communication strategies &amp;amp; skills within the multidisciplinary team to ensure patient safety &amp;amp; dignity&lt;/li&gt;\n&lt;li&gt;Use effective communication skills to support the patient at different stages of their care&lt;/li&gt;\n&lt;li&gt;Identify barriers to communication, their potential impact &amp;amp; strategies for management&lt;/li&gt;\n&lt;li&gt;ensure your own behaviour supports others to work in ways that are consistent with individuals&#39; beliefs and preferences, that regard diversity positively and that support anti-discriminatory practice&lt;/li&gt;\n&lt;li&gt;Maintain care records that are fit for purpose &amp;amp; process them according to legislation&lt;/li&gt;\n&lt;li&gt;Formulate care plans including setting of timescales&lt;/li&gt;\n&lt;li&gt;Analyse &amp;amp; critically evaluate information collected &amp;amp; appropriately act upon it&lt;/li&gt;\n&lt;/ul&gt;\n&lt;/td&gt;\n&lt;td&gt;\n&lt;ul&gt;\n&lt;li&gt;The concept of confidentiality &amp;amp; the principles of information governance&lt;/li&gt;\n&lt;li&gt;The importance of communication in plain English;&#160; a range of verbal and non-verbal communication techniques appropriate to age, mental capacity &#160;cognitive abilitiesactive listening and observing skills&lt;/li&gt;\n&lt;li&gt;Communication theroies and how they are applicable to the perioperative environment&lt;/li&gt;\n&lt;li&gt;How a patients communication is affected by varying levels of consciousness&lt;/li&gt;\n&lt;li&gt;legal and work setting requirements on equality, diversity, discrimination and rights&lt;/li&gt;\n&lt;li&gt;The importance of providing patients with appropriate information to make informed decisions&lt;/li&gt;\n&lt;li&gt;The importance of managing records &amp;amp; information in accordance with legislation, protocols &amp;amp; guidelines, for example recording swab &amp;amp; instrument counts to ensure nothing is left behind in the patients body after surgery&lt;/li&gt;\n&lt;li&gt;Principles &amp;amp; practices of the consent process&lt;/li&gt;\n&lt;li&gt;Risk management &amp;amp; incident reporting processes in line with organisational policy&lt;/li&gt;\n&lt;li&gt;The impact of age, culture, ethnicity, gender, socio-economic status &amp;amp; spiritual or religious beliefs on communication&lt;/li&gt;\n&lt;/ul&gt;\n&lt;/td&gt;\n&lt;/tr&gt;\n&lt;/tbody&gt;\n&lt;/table&gt;\n&lt;p&gt;&#160;&lt;/p&gt;\n&lt;p&gt;&lt;span&gt;&lt;span class=&quot;reference&quot;&gt;&lt;a href=&quot;#_ednref1&quot;&gt;[i]&lt;/a&gt; View details about the care certificate on the Skills for Health website&#160; - http://www.skillsforhealth.org.uk/standards/item/216-the-care-certificate&#160;&lt;/span&gt;&lt;/span&gt;&lt;/p&gt;\n&lt;p&gt;&lt;span class=&quot;reference&quot;&gt;&lt;a name=&quot;_edn1&quot; href=&quot;#_ednref1&quot;&gt;[ii]&lt;/a&gt; HCPC Standards of Proficiency Operating Department Practitioners 2013 &lt;a href=&quot;http://www.hcpc-uk.org/registrants/standards/download/index.asp?id=46&quot;&gt;http://www.hcpc-uk.org/registrants/standards/download/index.asp?id=46&lt;/a&gt;&#160;&lt;/span&gt;&lt;/p&gt;\n&lt;p&gt;&lt;span class=&quot;reference&quot;&gt;&lt;a name=&quot;_edn2&quot; href=&quot;#_ednref2&quot;&gt;[iii]&lt;/a&gt; College of Operating Department Practitioners Scope of Practice &lt;a href=&quot;https://www.rcoa.ac.uk/sites/default/files/CODP-Scope-Practice2009.pdf&quot;&gt;https://www.rcoa.ac.uk/sites/default/files/CODP-Scope-Practice2009.pdf&lt;/a&gt;&lt;/span&gt;&lt;/p&gt;\n&lt;p&gt;&lt;span class=&quot;reference&quot;&gt;&lt;a name=&quot;_edn3&quot; href=&quot;#_ednref3&quot;&gt;[iv]&lt;/a&gt; Legislation, standards and protocol see footnotes above plus:&#160; 1. &lt;a href=&quot;http://www.hcpc-uk.org/assets/documents/10004EDFStandardsofconduct,performanceandethics.pdf&quot;&gt;http://www.hcpc-uk.org/assets/documents/10004EDFStandardsofconduct,performanceandethics.pdf&lt;/a&gt;; &#160;2. &lt;a href=&quot;http://www.hpc-uk.org/registrants/cpd/standards/&quot;&gt;http://www.hpc-uk.org/registrants/cpd/standards/&lt;/a&gt;; 3. &lt;a href=&quot;https://www.afpp.org.uk/books-journals/afpppublications/Standards-Recommendations-for-Safe-Perioperative-Practice-2016&quot;&gt;https://www.afpp.org.uk/books-journals/afpppublications/Standards-Recommendations-for-Safe-Perioperative-Practice-2016&lt;/a&gt;; 4. &lt;a href=&quot;https://www.england.nhs.uk/wp-content/uploads/2015/09/natssips-safety-standards.pdf&quot;&gt;https://www.england.nhs.uk/wp-content/uploads/2015/09/natssips-safety-standards.pdf&lt;/a&gt;; 5. &lt;a href=&quot;http://www.nrls.npsa.nhs.uk/resources/?entryid45=59860&quot;&gt;http://www.nrls.npsa.nhs.uk/resources/?entryid45=59860&lt;/a&gt;; 6. &lt;a href=&quot;http://www.nrls.npsa.nhs.uk/resources/?EntryId45=92901&quot;&gt;http://www.nrls.npsa.nhs.uk/resources/?EntryId45=92901&lt;/a&gt;&lt;/span&gt;&lt;/p&gt;\n&lt;p&gt;&#160;&lt;/p&gt;",
  "occupationalSummary": "&lt;p&gt;Operating Department Practitioners (ODPs) are registered healthcare professionals specialising in caring for people of all ages before, during &amp;amp; after surgery. ODPs therefore mainly work in operating departments. They work alongside other professionals (such as doctors and nurses) and take a lead role in ensuring a patient is safe during each stage of a patient’s journey through the operating theatre. ODPs must continually make professional decisions to ensure the patient receives the best care before, during and after their surgery. ODPs also ensure that the operating theatre environment is safe and effective and therefore have expertise in the management of specialist equipment &amp;amp; materials in a highly technical environment, for example handling surgical instruments, checking anaesthetic equipment, moving patients and giving medication ODPs must demonstrate confidence, compassion, competence &amp;amp; effective judgement; being responsible for their decisions. They must use evidence based practice to inform &amp;amp; evaluate the effectiveness of the actions they take with the aim of continually improving outcomes for patients. They are responsible for ensuing their own professional knowledge and skills through continuous professional development (CPD)&amp;amp; support the development of others.&lt;/p&gt;",
  "knowledges": [
    {
      "knowledgeId": "4d220e43-6071-485b-b52c-c6ade7705647",
      "detail": "Professional practice"
    },
    {
      "knowledgeId": "419ada14-8a08-4feb-9be3-3d8898078a2d",
      "detail": "How to apply professional knowledge, skills & experience in partnership with other professionals to optimise outcomes for patients"
    },
    {
      "knowledgeId": "e8bf264b-fb51-435b-8b16-6c165f3a9d9e",
      "detail": "Normal anatomy & physiology of the human body & impact of disease, & trauma processes"
    },
    {
      "knowledgeId": "e2adc40b-c2ba-4584-87fd-5b47e6e37828",
      "detail": "Physiological parameters & how to interpret changes/deviations"
    },
    {
      "knowledgeId": "bc2ac014-559d-4971-9f9d-972d5b542076",
      "detail": "How to order, store, issue, prepare & administer prescribed drugs & monitor their effects"
    },
    {
      "knowledgeId": "5d94628a-70da-4524-82f9-f2133803baf8",
      "detail": "The drugs that are used in ODP practice & how they affect the body"
    },
    {
      "knowledgeId": "1b05540e-1bb7-4b9e-b063-b3447d6f0618",
      "detail": "Safe practices in the use of medical devices use for diagnostic, monitoring or therapeutic purposes"
    },
    {
      "knowledgeId": "bc1cc561-7852-4c83-be47-9fc88e4a8df6",
      "detail": "Effective innovation, change management & planning techniques; theories of change mangement including tools & techniques in how to apply them"
    },
    {
      "knowledgeId": "fdd39740-025e-4164-8418-a38013a20d53",
      "detail": "The principles & practices in the management of anaesthetic & surgical emergencies, e.g. a major haemorrhage or anaphylaxis"
    },
    {
      "knowledgeId": "c2842ab5-ab90-4b5c-a095-1e6930b69a80",
      "detail": "The management & processes involved in the administration of blood & blood products"
    },
    {
      "knowledgeId": "40c13ab1-ce1d-4ec0-99a4-d37c2299cedc",
      "detail": "The use of research methodologies used in Operating Department Practice; the principles & applications of evidence based practice."
    },
    {
      "knowledgeId": "42876979-9517-4c9f-8b5a-e23a09ce3e59",
      "detail": "The principles of hand hygiene & asepsis"
    },
    {
      "knowledgeId": "5a4d2f56-89c6-433c-9859-134f027850d9",
      "detail": "Sterilisation & decontamination of equipment processes"
    },
    {
      "knowledgeId": "d81ad0b4-04cf-45ef-b9cd-afe3fde69c7f",
      "detail": "Safeguarding processes & how to raise concerns"
    },
    {
      "knowledgeId": "b28e8cba-ff09-4e00-8549-3750d3f0c64f",
      "detail": "Infection prevention & control policies & procedures"
    },
    {
      "knowledgeId": "f119f69b-210a-4769-b1d6-a1dddd6d152a",
      "detail": "The role of the surgical first assistant in assisting with surgical interventions"
    },
    {
      "knowledgeId": "5a1c419a-1d77-4507-90af-3dea37c5a05c",
      "detail": "Appropriate Moving & Handling Techniques"
    },
    {
      "knowledgeId": "4961a199-6d4c-4a2c-b275-445a9b230ece",
      "detail": "The structure & function of health & social care services in the UK"
    },
    {
      "knowledgeId": "c0233342-73fa-40af-9f91-5727c8bc09af",
      "detail": "Professional values & behaviours"
    },
    {
      "knowledgeId": "daf03c95-753f-4c36-bcc2-151e0bc1f56c",
      "detail": "How to assess the nature & complexity of a patients needs"
    },
    {
      "knowledgeId": "238d4cc2-6919-4b46-a3cd-609e873fa952",
      "detail": "How to adapt practice to meet the needs of patients within the scope of ODP practice, national/local policy & latest evidence"
    },
    {
      "knowledgeId": "9aa727f2-b9e0-42df-a54e-295b19d0516d",
      "detail": "The importance of maintaining patients comfort & dignity at all times"
    },
    {
      "knowledgeId": "6dfafc04-83d0-4f92-a371-d46e79b885e3",
      "detail": "The requirements of Duty of candour regulations"
    },
    {
      "knowledgeId": "0e257b69-9ca3-4716-bba5-025feedc94e9",
      "detail": "Legal & ethical issues pertinent to ODP practice"
    },
    {
      "knowledgeId": "a37dcec3-c63f-41e6-b5db-0e489e92d4b6",
      "detail": "Theatre etiquette"
    },
    {
      "knowledgeId": "197f862d-9ec0-46c3-b1bf-ed1d6fea3729",
      "detail": "How to interact with patients, relatives & colleagues in a professional manner"
    },
    {
      "knowledgeId": "e5f20afd-bf2e-46ed-8535-585a7deaf7f1",
      "detail": "Professional standards"
    },
    {
      "knowledgeId": "97f891dc-d647-4d1e-81c6-7a761827d5d5",
      "detail": "The legislation, standards and protocol relating to ODP practice [iii]."
    },
    {
      "knowledgeId": "3f7a0cb0-7ce2-458f-ae88-762ad5cc1867",
      "detail": "Leadership, management & partnership working"
    },
    {
      "knowledgeId": "de24d0b6-6bda-4cbd-93ca-7659c2bff5e9",
      "detail": "The concept of leadership & using personal initiative"
    },
    {
      "knowledgeId": "0c7b82be-f404-4030-b603-fbcbc3184a40",
      "detail": "The value of participation in training, supervision & mentoring"
    },
    {
      "knowledgeId": "ce467721-b042-4e81-8b0e-7391675ba64d",
      "detail": "The importance of working collaboratively with those who provide services"
    },
    {
      "knowledgeId": "72cf406c-95e1-43f2-a946-4d297faa5855",
      "detail": "How to reflect effectively & facilitate change in perioperative practice"
    },
    {
      "knowledgeId": "ad2f7d78-db4d-446e-b521-a4d5f4e3ced5",
      "detail": "Team dynamics, communication & patient safety with a reference to human factors"
    },
    {
      "knowledgeId": "5af5951c-23cd-4c5e-92ea-e460ad9a15e0",
      "detail": "The value & impact of research, audit & evaluation on operating department practice"
    },
    {
      "knowledgeId": "b49a068f-374e-4a89-aec5-b803e15936f7",
      "detail": "The importance of maintaining own health & well-being; ways to manage & reduce occupational stress"
    },
    {
      "knowledgeId": "1c5a1848-c023-4f04-aad5-e53e332315ff",
      "detail": "Communication & information"
    },
    {
      "knowledgeId": "b2c693d2-3781-4a1e-99f3-1c53f54a574e",
      "detail": "The concept of confidentiality & the principles of information governance"
    },
    {
      "knowledgeId": "28730779-e6ef-4e45-b8e0-8aa107367861",
      "detail": "The importance of communication in plain English;  a range of verbal and non-verbal communication techniques appropriate to age, mental capacity  cognitive abilitiesactive listening and observing skills"
    },
    {
      "knowledgeId": "a5ba5d90-bdf3-43f3-82c6-9d700f023c5a",
      "detail": "Communication theroies and how they are applicable to the perioperative environment"
    },
    {
      "knowledgeId": "a9217c74-f9e1-4d72-956e-681c211120da",
      "detail": "How a patients communication is affected by varying levels of consciousness"
    },
    {
      "knowledgeId": "f9b12089-aaa3-4d8a-b244-ec48a6384306",
      "detail": "legal and work setting requirements on equality, diversity, discrimination and rights"
    },
    {
      "knowledgeId": "194f9547-3d44-438a-a122-9dc483fb23e2",
      "detail": "The importance of providing patients with appropriate information to make informed decisions"
    },
    {
      "knowledgeId": "937ca2b4-3b58-486f-b4bb-2737f429a5bc",
      "detail": "The importance of managing records & information in accordance with legislation, protocols & guidelines, for example recording swab & instrument counts to ensure nothing is left behind in the patients body after surgery"
    },
    {
      "knowledgeId": "a61de229-92e2-4239-a048-fe6ecf19a05c",
      "detail": "Principles & practices of the consent process"
    },
    {
      "knowledgeId": "15a279ad-054c-4612-a687-ae0813650e71",
      "detail": "Risk management & incident reporting processes in line with organisational policy"
    },
    {
      "knowledgeId": "e24411c9-3147-465e-9e18-a1cb76913c15",
      "detail": "The impact of age, culture, ethnicity, gender, socio-economic status & spiritual or religious beliefs on communication"
    }
  ],
  "behaviours": [],
  "skills": [
    {
      "skillId": "178bfb2d-c302-47bf-bb72-3754a3af2d3c",
      "detail": "Practice as an autonomous ODP, assessing patients in theatres & associated areas, exercising professional judgement to establish patient centred goals, & to accept, plan, initiate, modify, refer or cease treatment within prescribed limits"
    },
    {
      "skillId": "fe751e7b-accb-4232-800f-d2e228cf6976",
      "detail": "Recognise disease & trauma processes relevant to perioperative care"
    },
    {
      "skillId": "074d258e-7957-4bd6-8a6c-5061172d795a",
      "detail": "Accurately calculate & record prescribed drug doses"
    },
    {
      "skillId": "14ebf465-1ee2-4ab1-a7b3-e1ffb2c8c855",
      "detail": "Change practice to account for new developments or changing contexts in what constitutes best practice in perioperative care,  through effective change management"
    },
    {
      "skillId": "cfadfaa1-ddd3-4b3c-8587-ca71871dd034",
      "detail": "Respond appropriately  to emergency situations"
    },
    {
      "skillId": "c8adf924-a784-4609-a71f-ceeec874b7aa",
      "detail": "Conduct appropriate diagnostic, monitoring, treatment & therapy procedures safely & effectively"
    },
    {
      "skillId": "de9e0f65-2b11-4882-bfbd-8b0b3402c184",
      "detail": "Undertake anaesthetic, surgical & post-anaesthesia care interventions including managing airways, cannulation, catheterisation & manual handling/positioning"
    },
    {
      "skillId": "e6bcbc06-5f25-4371-a859-f40f20562ddd",
      "detail": "Monitor airway, breathing & circulation"
    },
    {
      "skillId": "292fd2c3-af37-46f9-9eaa-95473050cc51",
      "detail": "Monitor & record fluid balance & administer prescribed fluids appropriately"
    },
    {
      "skillId": "8da5f9b6-6823-4b3c-a4df-c01a7741a578",
      "detail": "Monitor the effects of drugs & take appropriate action is response to significant change"
    },
    {
      "skillId": "682b67ef-64f5-471e-a12e-45d44588c5cc",
      "detail": "Assess & monitor individuals pain status & administer prescribed pain relief appropriately"
    },
    {
      "skillId": "51b00a6a-d49a-49e1-b1ac-03150d3590a4",
      "detail": "Select appropriate techniques & equipment; undertake & record thorough assessments & investigations."
    },
    {
      "skillId": "d09a15c6-e397-40c9-a265-8124f6961f18",
      "detail": "Maintaining Basic, Intermediate or Advanced Life Support qualifications where appropriate"
    },
    {
      "skillId": "753b7822-eda5-4d09-a7ec-74741127bbd4",
      "detail": "Assist anaesthesia with the use of medical devices & pharmacological (drugs) means"
    },
    {
      "skillId": "fa75d103-e9c7-4165-a6bd-33b5e1ebfb01",
      "detail": "Maintain a sterile working area & safely & effectively perform aseptic technique (including scrubbing, gloving & gowning)"
    },
    {
      "skillId": "f7e4ad7d-ce3c-4317-8141-28f1098320e6",
      "detail": "Perform scrub skills according in accordance with Perioperative Care Collaborative statement"
    },
    {
      "skillId": "e305df42-a5a4-4672-a431-92264a0d13c2",
      "detail": "Recognise & take account of needs & diversity of individuals"
    },
    {
      "skillId": "66ddc03d-664a-405c-901b-5e9d8ba88534",
      "detail": "Shape or structure your practice according to evidence based practice"
    },
    {
      "skillId": "d31d4a31-304e-4158-8348-1997e9ce0153",
      "detail": "Practice in a manner ensuring equality & act as an advocate for patients. Demonstrate care, compassion, confidence, courage, communication & commitment for patients at their most vulnerable."
    },
    {
      "skillId": "67335cfe-e864-4fc2-be24-7d68323a826e",
      "detail": "Maintain the patients dignity at all times"
    },
    {
      "skillId": "b6b30e89-b877-477f-a1a8-18963f1697cf",
      "detail": "Demonstrate an open, honest & courteous approach to patients relatives & colleagues"
    },
    {
      "skillId": "9733484e-58c1-4621-ba13-5c267b9b37b7",
      "detail": "Practice within the Health and Care Professions Council (HCPC) Standards of Proficiency for ODP’s[i] & The College of Operating Department Practitioners Scope of Practice[ii]"
    },
    {
      "skillId": "3752171e-149e-4af0-9630-7238cecce444",
      "detail": "Effectively lead manage & delegate colleagues, working as part of the surgical team"
    },
    {
      "skillId": "b1e95aed-081f-476a-a6ba-fa441eead6eb",
      "detail": "Work collaboratively throughout the patients perioperative journey with the surgical team & others"
    },
    {
      "skillId": "1983ee1c-dce5-4069-b038-33a18888a157",
      "detail": "Use the evidence base to promote innovation & improvement in operating department practice"
    },
    {
      "skillId": "222a0f30-debf-4217-a83e-a115ccc966f4",
      "detail": "Actively participate in audit, training & review activities"
    },
    {
      "skillId": "5c5a6e04-1f3e-4dca-a78b-ea08dab727c0",
      "detail": "Manage yourself in emergency & stressful situations."
    },
    {
      "skillId": "46529d4b-b090-449b-a18c-26b7deec03ba",
      "detail": "Demonstrate self-awareness & impact on others."
    },
    {
      "skillId": "04978b6e-42e1-42ee-81d7-d67efb7182c5",
      "detail": "Reflect on own practice & challenge self & others"
    },
    {
      "skillId": "313dddf0-90a4-451d-943a-eae7773c06a5",
      "detail": "Safeguard confidential information, relating to patients at all times, consistently applying data protection principles"
    },
    {
      "skillId": "2b244b01-afb0-4a1b-8080-dfad385df9cc",
      "detail": "Apply a range of communication strategies & skills within the multidisciplinary team to ensure patient safety & dignity"
    },
    {
      "skillId": "012296bb-80a0-4958-9588-3b4fd1d8813c",
      "detail": "Use effective communication skills to support the patient at different stages of their care"
    },
    {
      "skillId": "2d9d4aaa-5612-4537-a6d0-450f66d26fd5",
      "detail": "Identify barriers to communication, their potential impact & strategies for management"
    },
    {
      "skillId": "ffdec99f-5f1e-4af0-8934-acbf2b8b6cd2",
      "detail": "ensure your own behaviour supports others to work in ways that are consistent with individuals' beliefs and preferences, that regard diversity positively and that support anti-discriminatory practice"
    },
    {
      "skillId": "0b8a11f8-a7ee-4afa-9e2a-f757412f465b",
      "detail": "Maintain care records that are fit for purpose & process them according to legislation"
    },
    {
      "skillId": "c70e5767-07fd-43b6-b43f-b826be43b02b",
      "detail": "Formulate care plans including setting of timescales"
    },
    {
      "skillId": "31838dba-1c04-4509-b16e-905da3f57647",
      "detail": "Analyse & critically evaluate information collected & appropriately act upon it"
    }
  ],
  "optionsUnstructuredTemplate": [],
  "proposalApproved": "",
  "standardApproved": "",
  "standardPublished": "true",
  "epaApprovalDate": "",
  "epaPublished": "true",
  "fundingApprovalDate": "",
  "eQAProvider": {
    "providerName": "Office for Students",
    "contactName": "",
    "contactAddress": "Westward House<br>Lime Kiln Close<br>Stoke Gifford<br>BRISTOL<br>BS34 8SR<br>tel 0117 931 7317",
    "contactEmail": "apprenticeshipEQA@officeforstudents.org.uk",
    "webLink": "https://www.officeforstudents.org.uk/"
  },
  "approvedForDelivery": "2018-06-28T00:00:00 +00:00",
  "integratedApprenticeship": null,
  "integration": null,
  "integratedDegree": "integrated degree",
  "tbReference": "TB0268",
  "tbMainContact": "healthcare.trailblazer@skillsforhealth.org.uk",
  "involvedEmployers": "Alder Hey Children's Hospital, Basildon and Thurrock University Hospitals NHS Foundation Trust, Birmingham Children's Hospital, BMI Healthcare, Bradford Teaching Hospitals NHS Foundation Trust, Colchester Hospital University, College of Operating Department Practitioners, Doncaster and Bassetlaw Hospitals NHS FT, Luton and Dunstable University Hospital, Milton Keynes University Hospital, North Bristol NHS Trust, Royal Liverpool University Hospital, Royal United Hospital Bath NHS Foundation Trust, Salisbury NHS Foundation Trust, Southend University Hospital NHS Foundation Trust, University Hospital of South Manchester NHS Foundation Trust, University Hospitals of Morecambe Bay NHS Foundation Trust, Sheffield Hallam University, Staffordshire University, University of Derby, University of Central Lancashire, The Association for Perioperative Practice, Health Education England, Ramsay UK Healthcare Group",
  "otherInvolvedStakeholders": "",
  "regulated": true,
  "regulatedBody": "Health and Care Professions Council",
  "coreAndOptions": false,
  "typicalJobTitles": [],
  "greenJobTitles": [],
  "englishAndMathsQualifications": "",
  "reviewDetails": "this apprenticeship will be reviewed in accordance with our change request policy.",
  "pathway": "Health",
  "cluster": "Health Professional",
  "clusterId": "6",
  "clusterDescription": "Provide direct patient contact along with high quality diagnosis and care working independently and with other health professionals",
  "createdDate": "2017-11-14T17:10:55 +00:00",
  "lastUpdated": "2022-11-30T00:00:00 +00:00",
  "occupationalStandardApprovalDate": "2018-06-28T00:00:00 +00:00",
  "banners": "",
  "occupationCode": "OCC0582",
  "occupationalStandardUrl": "https://instituteforapprenticeships.org/apprenticeships/st0582-v1-0?view=standard#OccupationalStandard",
  "standardPageUrl": "https://instituteforapprenticeships.org/apprenticeships/st0582-v1-0",
  "qualifications": [],
  "professionalRecognition": [],
  "duties": [],
  "options": [],
  "regulationDetail": [
    {
      "name": "Training provider",
      "webLink": "",
      "approved": true
    },
    {
      "name": "EPAO",
      "webLink": "",
      "approved": true
    }
  ],
  "optionsUnstructuredKsbMapping": [],
  "careerStarter": false,
  "coronationEmblem": false,
  "publishDate": "2022-11-30T00:00:00"
}